python_PixelArt/__init__.py
python_PixelArt-0.3.3.dist-info/LICENSE
python_PixelArt-0.3.3.dist-info/LICENSE_FR
python_PixelArt-0.3.3.dist-info/METADATA
python_PixelArt-0.3.3.dist-info/WHEEL
python_PixelArt-0.3.3.dist-info/top_level.txt
python_PixelArt-0.3.3.dist-info/RECORD
